resistencias/__init__.py
resistencias/matematicas.py
resistencias/tuberias.py
resistencias-0.1.2.dist-info/METADATA
resistencias-0.1.2.dist-info/WHEEL
resistencias-0.1.2.dist-info/RECORD
