Metadata-Version: 2.1
Name: resistencias
Version: 0.1.2
Summary: 
Home-page: https://github.com/lsquinones/resistencias
Author: Santiago Quiñones
Author-email: lsquinones@gmail.com
Requires-Python: >=3.10.0,<3.12
Classifier: Programming Language :: Python :: 3
Classifier: Programming Language :: Python :: 3.10
Classifier: Programming Language :: Python :: 3.11
Requires-Dist: matplotlib (>=3.9.1,<4.0.0)
Requires-Dist: networkx (>=3.3,<4.0)
Requires-Dist: numpy (>=2.0.0,<3.0.0)
Project-URL: Repository, https://github.com/lsquinones/resistencias
Project-URL: documentation, https://github.com/lsquinones/resistencias#readme
Project-URL: homepage, https://github.com/lsquinones/resistencias
Project-URL: repository, https://github.com/lsquinones/resistencias
